scrapingant_client/__init__.py
scrapingant_client/client.py
scrapingant_client/constants.py
scrapingant_client/cookie.py
scrapingant_client/errors.py
scrapingant_client/headers.py
scrapingant_client/proxy_type.py
scrapingant_client/response.py
scrapingant_client/utils.py
tests/__init__.py
tests/test_cookies.py
tests/test_exceptions.py
tests/test_headers.py
tests/test_integration.py
scrapingant_client-2.1.0.dist-info/METADATA
scrapingant_client-2.1.0.dist-info/WHEEL
scrapingant_client-2.1.0.dist-info/top_level.txt
scrapingant_client-2.1.0.dist-info/RECORD
