Metadata-Version: 2.1
Name: scrapingant-client
Version: 2.1.0
Summary: Official python client for the ScrapingAnt API.
Home-page: https://github.com/ScrapingAnt/scrapingant-client-python
Author: andrii.kovalenko
Author-email: adrekoval@gmail.com
License: Apache-2.0
Keywords: scrapingant api scraper scraping
Classifier: Operating System :: OS Independent
Classifier: Programming Language :: Python :: 3.5
Classifier: Programming Language :: Python :: 3.6
Classifier: Programming Language :: Python :: 3.7
Classifier: Programming Language :: Python :: 3.8
Classifier: Programming Language :: Python :: 3.9
Classifier: Topic :: Software Development :: Libraries :: Python Modules
Classifier: Topic :: Internet :: WWW/HTTP :: Browsers
Classifier: License :: OSI Approved :: Apache Software License
Requires-Python: ~=3.7
Requires-Dist: requests <3,>=2
Provides-Extra: async
Requires-Dist: httpx <1 ; extra == 'async'
Provides-Extra: dev
Requires-Dist: pytest <8,>=7 ; extra == 'dev'
Requires-Dist: flake8 <8,>=7 ; extra == 'dev'
Requires-Dist: responses <1,>=0 ; extra == 'dev'
Requires-Dist: pytest-httpx <1,>=0 ; extra == 'dev'
Requires-Dist: pytest-asyncio <1,>=0 ; extra == 'dev'
